[
  {
    "id": "art-sierra-club-bay-chapter-m004-live-chunk-001",
    "sourceId": "src-sierra-club-bay-chapter",
    "artifactId": "art-sierra-club-bay-chapter-m004-live",
    "order": 1,
    "text": "2026 Endorsements | Sierra Club\nSkip to main content\nShape Combined Shape Combined Shape Shape Combined Shape ic_video_youtube_black SC Logo_Horiz Web Black\n2026 Endorsements\nThe following are the Sierra Club's endorsements for the June 2nd, 2026, Statewide Direct Primary Election and November 3rd, 2026 Midterm Election.\nThe last day to register to vote in the primary is 15 days earlier, May 18th, 2026.\nThe last day to register for the midterm is 15 days earlier, October 19th, 2026.\nThis page will be updated as endorsements are finalized. Read about our endorsement process here .\nFederal Candidates\nUS Representative, District 2: Jared Huffman\nUS Representative, District 10: Mark DeSaulnier\nUS Representative: District 11: Scott Wiener\nUS Representative: District 12: Lateefah Simon\nState Candidates\nState Senate, District 2: Damon Connolly\nState Assembly, District 17: Matt Haney\nState Assembly, District 19: Catherine Stefani\nInsurance Commissioner: Ben Allen\nAttorney General: Rob Bonta\nController: Malia Cohen\nSecretary of State: Shirley Webber\nRegional Ballot Measures\nMarin / Sonoma\nSMART Rail Transit Tax Extension: YES!\nAlameda / Contra Costa / San Francisco / San Mateo / Santa",
    "startOffset": 0,
    "endOffset": 1194,
    "charCount": 1194
  },
  {
    "id": "art-sierra-club-bay-chapter-m004-live-chunk-002",
    "sourceId": "src-sierra-club-bay-chapter",
    "artifactId": "art-sierra-club-bay-chapter-m004-live",
    "order": 2,
    "text": "Clara\nConnect Bay Area : YES! (on the Midterm ballot in the fall)\nCounty Candidates\nAlameda\nBoard of Supervisors: Lena Tam\nCity Ballot Measures\nSan Francisco\nMeasure A, Earthquake Safety and Emergency Response Bond : YES!\nCity Candidates\nSan Francisco\nBoard of Supervisors District 2: Stephen Sherrill\nBerkeley\nCity Council District 4: Igor Tregub\nCity Council District 6: Kevin Jenkins\nCity Council District 8: Mark Humbert\nEl Cerrito\nCity Council: Gabe Quinto\nCity Council: Carolyn Wysinger\nRichmond\nCity Council: Doria Robinson\nCity Council: Cesar Zepeda\nSan Francisco\nStronger MUNI for All : Yes! (on the Midterm ballot in the fall)\nSpecial District Candidates\nAC Transit Ward 4: Sarah Syed\nPages with political endorsements have a simplified web design. Please click the back button to return to the previous screen or “Home” to go to this website’s home page. Sierra Club National Endorsements",
    "startOffset": 1195,
    "endOffset": 2094,
    "charCount": 899
  }
]
